odoo/addons/sm_connect/__init__.py
odoo/addons/sm_connect/__manifest__.py
odoo/addons/sm_connect/demo_credentials.json
odoo/addons/sm_connect/models/__init__.py
odoo/addons/sm_connect/models/credential_loader.py
odoo/addons/sm_connect/models/models_sm_carsharing_api_utils.py
odoo/addons/sm_connect/models/models_sm_carsharing_db_utils.py
odoo/addons/sm_connect/models/models_sm_wordpress_db_utils.py
odoo/addons/sm_connect/security/ir.model.access.csv
odoo11_addon_sm_connect-11.0.0.0.2.dist-info/METADATA
odoo11_addon_sm_connect-11.0.0.0.2.dist-info/WHEEL
odoo11_addon_sm_connect-11.0.0.0.2.dist-info/top_level.txt
odoo11_addon_sm_connect-11.0.0.0.2.dist-info/RECORD
